verdandi/__init__.py
verdandi/__main__.py
verdandi/benchmark.py
verdandi/cli.py
verdandi/loader.py
verdandi/main.py
verdandi/result.py
verdandi/runner.py
verdandi/utils.py
verdandi-0.2.3.dist-info/entry_points.txt
verdandi-0.2.3.dist-info/LICENSE
verdandi-0.2.3.dist-info/WHEEL
verdandi-0.2.3.dist-info/METADATA
verdandi-0.2.3.dist-info/RECORD
