Metadata-Version: 2.1
Name: verdandi
Version: 0.2.3
Summary: Benchmarking framework
Home-page: https://github.com/exler/verdandi
License: MIT
Keywords: benchmark,performance
Author: Kamil Marut
Author-email: kamil@kamilmarut.com
Requires-Python: >=3.6.2,<4.0
Classifier: Environment :: Console
Classifier: Intended Audience :: Developers
Classifier: License :: OSI Approved :: MIT License
Classifier: Operating System :: OS Independent
Classifier: Programming Language :: Python :: 3
Classifier: Programming Language :: Python :: 3.10
Classifier: Programming Language :: Python :: 3.7
Classifier: Programming Language :: Python :: 3.8
Classifier: Programming Language :: Python :: 3.9
Classifier: Topic :: Software Development :: Testing
Classifier: Topic :: System :: Benchmark
Project-URL: Bug Tracker, https://github.com/exler/verdandi/issues
Project-URL: Repository, https://github.com/exler/verdandi
